MANIFEST.in
README.md
setup.cfg
setup.py
zdairi/__init__.py
zdairi/usage.py
zdairi/zdairi.py
zdairi/zeppelincmd.py
zdairi.egg-info/PKG-INFO
zdairi.egg-info/SOURCES.txt
zdairi.egg-info/dependency_links.txt
zdairi.egg-info/entry_points.txt
zdairi.egg-info/requires.txt
zdairi.egg-info/top_level.txt